setup.py
package_name/__init__.py
package_name.egg-info/PKG-INFO
package_name.egg-info/SOURCES.txt
package_name.egg-info/dependency_links.txt
package_name.egg-info/top_level.txt