Metadata-Version: 1.0
Name: package_name
Version: 0.1
Summary: Package Description
Home-page: https://github.com/yourself/package_name
Author: UNKNOWN
Author-email: UNKNOWN
License: UNKNOWN
Platform: UNKNOWN
